[{"Asset Tag": "25-Jul-24", "Serial Number": null, "Product": "MacBook Pro COMPLETED Apple 11.0", "Model": "COMPLETED", "Hardware Type": "M3 Pro", "CPU Type": "11.0", "CPU Cores": "14.0", "GPU Cores": "36.0", "Memory": "512.0", "Hard Drive": null, "Status": "INCLUDED", "Customer": "NEW", "Country": null, "PO": "A2442", "Receiving Date": null, "Condition": "ADP000", "Diagnostic": "MacBook Pro 14\" Apple M3 Pro 11-Core CPU 14-Core GPU 36GB RAM 512GB SSD", "Erased": "Wise", "Keyboard": "SGWV41VXHGJ", "Charger": "IN STOCK", "Included": null}, {"Asset Tag": "25-Jul-24", "Serial Number": null, "Product": "MacBook Pro COMPLETED Apple 11.0", "Model": "COMPLETED", "Hardware Type": "M3 Pro", "CPU Type": "11.0", "CPU Cores": "14.0", "GPU Cores": "36.0", "Memory": "512.0", "Hard Drive": null, "Status": "INCLUDED", "Customer": "NEW", "Country": null, "PO": "A2442", "Receiving Date": null, "Condition": "ADP000", "Diagnostic": "MacBook Pro 14\" Apple M3 Pro 11-Core CPU 14-Core GPU 36GB RAM 512GB SSD", "Erased": "Wise", "Keyboard": "SG04HR7F5FJ", "Charger": "IN STOCK", "Included": null}, {"Asset Tag": "25-Jul-24", "Serial Number": null, "Product": "MacBook Pro COMPLETED Apple 11.0", "Model": "COMPLETED", "Hardware Type": "M3 Pro", "CPU Type": "11.0", "CPU Cores": "14.0", "GPU Cores": "36.0", "Memory": "512.0", "Hard Drive": null, "Status": "INCLUDED", "Customer": "NEW", "Country": null, "PO": "A2442", "Receiving Date": null, "Condition": "ADP000", "Diagnostic": "MacBook Pro 14\" Apple M3 Pro 11-Core CPU 14-Core GPU 36GB RAM 512GB SSD", "Erased": "Wise", "Keyboard": "SC956QXWQVT", "Charger": "IN STOCK", "Included": null}, {"Asset Tag": "25-Jul-24", "Serial Number": null, "Product": "MacBook Pro COMPLETED Apple 11.0", "Model": "COMPLETED", "Hardware Type": "M3 Pro", "CPU Type": "11.0", "CPU Cores": "14.0", "GPU Cores": "36.0", "Memory": "512.0", "Hard Drive": null, "Status": "INCLUDED", "Customer": "NEW", "Country": null, "PO": "A2442", "Receiving Date": null, "Condition": "ADP000", "Diagnostic": "MacBook Pro 14\" Apple M3 Pro 11-Core CPU 14-Core GPU 36GB RAM 512GB SSD", "Erased": "Wise", "Keyboard": "SC4QHX9P6PM", "Charger": "IN STOCK", "Included": null}, {"Asset Tag": "25-Jul-24", "Serial Number": null, "Product": "MacBook Pro COMPLETED Apple 11.0", "Model": "COMPLETED", "Hardware Type": "M3 Pro", "CPU Type": "11.0", "CPU Cores": "14.0", "GPU Cores": "36.0", "Memory": "512.0", "Hard Drive": null, "Status": "INCLUDED", "Customer": "NEW", "Country": null, "PO": "A2442", "Receiving Date": null, "Condition": "ADP000", "Diagnostic": "MacBook Pro 14\" Apple M3 Pro 11-Core CPU 14-Core GPU 36GB RAM 512GB SSD", "Erased": "Wise", "Keyboard": "SFL446RX63T", "Charger": "IN STOCK", "Included": null}, {"Asset Tag": "25-Jul-24", "Serial Number": null, "Product": "MacBook Pro COMPLETED Apple 11.0", "Model": "COMPLETED", "Hardware Type": "M3 Pro", "CPU Type": "11.0", "CPU Cores": "14.0", "GPU Cores": "36.0", "Memory": "512.0", "Hard Drive": null, "Status": "INCLUDED", "Customer": "NEW", "Country": null, "PO": "A2442", "Receiving Date": null, "Condition": "ADP000", "Diagnostic": "MacBook Pro 14\" Apple M3 Pro 11-Core CPU 14-Core GPU 36GB RAM 512GB SSD", "Erased": "Wise", "Keyboard": "SH3YDC46NW1", "Charger": "IN STOCK", "Included": null}, {"Asset Tag": "25-Jul-24", "Serial Number": null, "Product": "MacBook Pro COMPLETED Apple 11.0", "Model": "COMPLETED", "Hardware Type": "M3 Pro", "CPU Type": "11.0", "CPU Cores": "14.0", "GPU Cores": "36.0", "Memory": "512.0", "Hard Drive": null, "Status": "INCLUDED", "Customer": "NEW", "Country": null, "PO": "A2442", "Receiving Date": null, "Condition": "ADP000", "Diagnostic": "MacBook Pro 14\" Apple M3 Pro 11-Core CPU 14-Core GPU 36GB RAM 512GB SSD", "Erased": "Wise", "Keyboard": "SGGX1WNLKPM", "Charger": "IN STOCK", "Included": null}, {"Asset Tag": "25-Jul-24", "Serial Number": null, "Product": "MacBook Pro COMPLETED Apple 11.0", "Model": "COMPLETED", "Hardware Type": "M3 Pro", "CPU Type": "11.0", "CPU Cores": "14.0", "GPU Cores": "36.0", "Memory": "512.0", "Hard Drive": null, "Status": "INCLUDED", "Customer": "NEW", "Country": null, "PO": "A2442", "Receiving Date": null, "Condition": "ADP000", "Diagnostic": "MacBook Pro 14\" Apple M3 Pro 11-Core CPU 14-Core GPU 36GB RAM 512GB SSD", "Erased": "Wise", "Keyboard": "SCP2VY2FCJ4", "Charger": "IN STOCK", "Included": null}, {"Asset Tag": "25-Jul-24", "Serial Number": null, "Product": "MacBook Pro COMPLETED Apple 11.0", "Model": "COMPLETED", "Hardware Type": "M3 Pro", "CPU Type": "11.0", "CPU Cores": "14.0", "GPU Cores": "36.0", "Memory": "512.0", "Hard Drive": null, "Status": "INCLUDED", "Customer": "NEW", "Country": null, "PO": "A2442", "Receiving Date": null, "Condition": "ADP000", "Diagnostic": "MacBook Pro 14\" Apple M3 Pro 11-Core CPU 14-Core GPU 36GB RAM 512GB SSD", "Erased": "Wise", "Keyboard": "SG4XPWQR9Y3", "Charger": "IN STOCK", "Included": null}, {"Asset Tag": "25-Jul-24", "Serial Number": null, "Product": "MacBook Pro COMPLETED Apple 11.0", "Model": "COMPLETED", "Hardware Type": "M3 Pro", "CPU Type": "11.0", "CPU Cores": "14.0", "GPU Cores": "36.0", "Memory": "512.0", "Hard Drive": null, "Status": "INCLUDED", "Customer": "NEW", "Country": null, "PO": "A2442", "Receiving Date": null, "Condition": "ADP000", "Diagnostic": "MacBook Pro 14\" Apple M3 Pro 11-Core CPU 14-Core GPU 36GB RAM 512GB SSD", "Erased": "Wise", "Keyboard": "SF47N2NK923", "Charger": "IN STOCK", "Included": null}, {"Asset Tag": "25-Jul-24", "Serial Number": null, "Product": "MacBook Pro COMPLETED Apple 8.0", "Model": "COMPLETED", "Hardware Type": "M2", "CPU Type": "8.0", "CPU Cores": "8.0", "GPU Cores": "8.0", "Memory": "256.0", "Hard Drive": null, "Status": "INCLUDED", "Customer": "NEW", "Country": null, "PO": "A2337", "Receiving Date": null, "Condition": "ADP000", "Diagnostic": "MacBook Air 13\" Apple M2 8-Core CPU 8-Core GPU 8GB RAM 256GB SSD", "Erased": "Wise", "Keyboard": "SCK2D7T4YPQ", "Charger": "IN STOCK", "Included": null}, {"Asset Tag": "25-Jul-24", "Serial Number": null, "Product": "MacBook Pro COMPLETED Apple 8.0", "Model": "COMPLETED", "Hardware Type": "M2", "CPU Type": "8.0", "CPU Cores": "8.0", "GPU Cores": "8.0", "Memory": "256.0", "Hard Drive": null, "Status": "INCLUDED", "Customer": "NEW", "Country": null, "PO": "A2337", "Receiving Date": null, "Condition": "ADP000", "Diagnostic": "MacBook Air 13\" Apple M2 8-Core CPU 8-Core GPU 8GB RAM 256GB SSD", "Erased": "Wise", "Keyboard": "SD2RJ6GXDYT", "Charger": "IN STOCK", "Included": null}, {"Asset Tag": "25-Jul-24", "Serial Number": null, "Product": "MacBook Pro COMPLETED Apple 8.0", "Model": "COMPLETED", "Hardware Type": "M2", "CPU Type": "8.0", "CPU Cores": "8.0", "GPU Cores": "8.0", "Memory": "256.0", "Hard Drive": null, "Status": "INCLUDED", "Customer": "NEW", "Country": null, "PO": "A2337", "Receiving Date": null, "Condition": "ADP000", "Diagnostic": "MacBook Air 13\" Apple M2 8-Core CPU 8-Core GPU 8GB RAM 256GB SSD", "Erased": "Wise", "Keyboard": "SJT6TQY4920", "Charger": "IN STOCK", "Included": null}, {"Asset Tag": "25-Jul-24", "Serial Number": null, "Product": "MacBook Pro COMPLETED Apple 8.0", "Model": "COMPLETED", "Hardware Type": "M2", "CPU Type": "8.0", "CPU Cores": "8.0", "GPU Cores": "8.0", "Memory": "256.0", "Hard Drive": null, "Status": "INCLUDED", "Customer": "NEW", "Country": null, "PO": "A2337", "Receiving Date": null, "Condition": "ADP000", "Diagnostic": "MacBook Air 13\" Apple M2 8-Core CPU 8-Core GPU 8GB RAM 256GB SSD", "Erased": "Wise", "Keyboard": "SHT2N9H5F6V", "Charger": "IN STOCK", "Included": null}, {"Asset Tag": "25-Jul-24", "Serial Number": null, "Product": "MacBook Pro COMPLETED Apple 8.0", "Model": "COMPLETED", "Hardware Type": "M2", "CPU Type": "8.0", "CPU Cores": "8.0", "GPU Cores": "8.0", "Memory": "256.0", "Hard Drive": null, "Status": "INCLUDED", "Customer": "NEW", "Country": null, "PO": "A2337", "Receiving Date": null, "Condition": "ADP000", "Diagnostic": "MacBook Air 13\" Apple M2 8-Core CPU 8-Core GPU 8GB RAM 256GB SSD", "Erased": "Wise", "Keyboard": "SC34WPL933J", "Charger": "IN STOCK", "Included": null}, {"Asset Tag": "25-Jul-24", "Serial Number": null, "Product": "MacBook Pro COMPLETED Apple 8.0", "Model": "COMPLETED", "Hardware Type": "M2", "CPU Type": "8.0", "CPU Cores": "8.0", "GPU Cores": "8.0", "Memory": "256.0", "Hard Drive": null, "Status": "INCLUDED", "Customer": "NEW", "Country": null, "PO": "A2337", "Receiving Date": null, "Condition": "ADP000", "Diagnostic": "MacBook Air 13\" Apple M2 8-Core CPU 8-Core GPU 8GB RAM 256GB SSD", "Erased": "Wise", "Keyboard": "SMT7Y9NG7JV", "Charger": "IN STOCK", "Included": null}, {"Asset Tag": "25-Jul-24", "Serial Number": null, "Product": "MacBook Pro COMPLETED Apple 8.0", "Model": "COMPLETED", "Hardware Type": "M2", "CPU Type": "8.0", "CPU Cores": "8.0", "GPU Cores": "8.0", "Memory": "256.0", "Hard Drive": null, "Status": "INCLUDED", "Customer": "NEW", "Country": null, "PO": "A2337", "Receiving Date": null, "Condition": "ADP000", "Diagnostic": "MacBook Air 13\" Apple M2 8-Core CPU 8-Core GPU 8GB RAM 256GB SSD", "Erased": "Wise", "Keyboard": "SL0341NQLFX", "Charger": "IN STOCK", "Included": null}, {"Asset Tag": "25-Jul-24", "Serial Number": null, "Product": "MacBook Pro COMPLETED Apple 8.0", "Model": "COMPLETED", "Hardware Type": "M2", "CPU Type": "8.0", "CPU Cores": "8.0", "GPU Cores": "8.0", "Memory": "256.0", "Hard Drive": null, "Status": "INCLUDED", "Customer": "NEW", "Country": null, "PO": "A2337", "Receiving Date": null, "Condition": "ADP000", "Diagnostic": "MacBook Air 13\" Apple M2 8-Core CPU 8-Core GPU 8GB RAM 256GB SSD", "Erased": "Wise", "Keyboard": "SGLWMVF3C4P", "Charger": "IN STOCK", "Included": null}, {"Asset Tag": "25-Jul-24", "Serial Number": null, "Product": "MacBook Pro COMPLETED Apple 8.0", "Model": "COMPLETED", "Hardware Type": "M2", "CPU Type": "8.0", "CPU Cores": "8.0", "GPU Cores": "8.0", "Memory": "256.0", "Hard Drive": null, "Status": "INCLUDED", "Customer": "NEW", "Country": null, "PO": "A2337", "Receiving Date": null, "Condition": "ADP000", "Diagnostic": "MacBook Air 13\" Apple M2 8-Core CPU 8-Core GPU 8GB RAM 256GB SSD", "Erased": "Wise", "Keyboard": "SH2MNQ4HKWW", "Charger": "IN STOCK", "Included": null}, {"Asset Tag": "25-Jul-24", "Serial Number": null, "Product": "MacBook Pro COMPLETED Apple 8.0", "Model": "COMPLETED", "Hardware Type": "M2", "CPU Type": "8.0", "CPU Cores": "8.0", "GPU Cores": "8.0", "Memory": "256.0", "Hard Drive": null, "Status": "INCLUDED", "Customer": "NEW", "Country": null, "PO": "A2337", "Receiving Date": null, "Condition": "ADP000", "Diagnostic": "MacBook Air 13\" Apple M2 8-Core CPU 8-Core GPU 8GB RAM 256GB SSD", "Erased": "Wise", "Keyboard": "SK625W7PV2L", "Charger": "IN STOCK", "Included": null}, {"Asset Tag": "25-Jul-24", "Serial Number": null, "Product": "MacBook Pro COMPLETED Apple 8.0", "Model": "COMPLETED", "Hardware Type": "M2", "CPU Type": "8.0", "CPU Cores": "8.0", "GPU Cores": "8.0", "Memory": "256.0", "Hard Drive": null, "Status": "INCLUDED", "Customer": "NEW", "Country": null, "PO": "A2337", "Receiving Date": null, "Condition": "ADP000", "Diagnostic": "MacBook Air 13\" Apple M2 8-Core CPU 8-Core GPU 8GB RAM 256GB SSD", "Erased": "Wise", "Keyboard": "SJ63YHW1232", "Charger": "IN STOCK", "Included": null}, {"Asset Tag": "25-Jul-24", "Serial Number": null, "Product": "MacBook Pro COMPLETED Apple 8.0", "Model": "COMPLETED", "Hardware Type": "M2", "CPU Type": "8.0", "CPU Cores": "8.0", "GPU Cores": "8.0", "Memory": "256.0", "Hard Drive": null, "Status": "INCLUDED", "Customer": "NEW", "Country": null, "PO": "A2337", "Receiving Date": null, "Condition": "ADP000", "Diagnostic": "MacBook Air 13\" Apple M2 8-Core CPU 8-Core GPU 8GB RAM 256GB SSD", "Erased": "Wise", "Keyboard": "SD3QY65P9NC", "Charger": "IN STOCK", "Included": null}, {"Asset Tag": "25-Jul-24", "Serial Number": null, "Product": "MacBook Pro COMPLETED Apple 8.0", "Model": "COMPLETED", "Hardware Type": "M2", "CPU Type": "8.0", "CPU Cores": "8.0", "GPU Cores": "8.0", "Memory": "256.0", "Hard Drive": null, "Status": "INCLUDED", "Customer": "NEW", "Country": null, "PO": "A2337", "Receiving Date": null, "Condition": "ADP000", "Diagnostic": "MacBook Air 13\" Apple M2 8-Core CPU 8-Core GPU 8GB RAM 256GB SSD", "Erased": "Wise", "Keyboard": "SMH4DW36JV9", "Charger": "IN STOCK", "Included": null}, {"Asset Tag": "25-Jul-24", "Serial Number": null, "Product": "MacBook Pro COMPLETED Apple 8.0", "Model": "COMPLETED", "Hardware Type": "M2", "CPU Type": "8.0", "CPU Cores": "8.0", "GPU Cores": "8.0", "Memory": "256.0", "Hard Drive": null, "Status": "INCLUDED", "Customer": "NEW", "Country": null, "PO": "A2337", "Receiving Date": null, "Condition": "ADP000", "Diagnostic": "MacBook Air 13\" Apple M2 8-Core CPU 8-Core GPU 8GB RAM 256GB SSD", "Erased": "Wise", "Keyboard": "SM232CYH6HK", "Charger": "IN STOCK", "Included": null}, {"Asset Tag": "25-Jul-24", "Serial Number": null, "Product": "MacBook Pro COMPLETED Apple 8.0", "Model": "COMPLETED", "Hardware Type": "M2", "CPU Type": "8.0", "CPU Cores": "8.0", "GPU Cores": "8.0", "Memory": "256.0", "Hard Drive": null, "Status": "INCLUDED", "Customer": "NEW", "Country": null, "PO": "A2337", "Receiving Date": null, "Condition": "ADP000", "Diagnostic": "MacBook Air 13\" Apple M2 8-Core CPU 8-Core GPU 8GB RAM 256GB SSD", "Erased": "Wise", "Keyboard": "SM7G6774VM2", "Charger": "IN STOCK", "Included": null}, {"Asset Tag": "25-Jul-24", "Serial Number": null, "Product": "MacBook Pro COMPLETED Apple 8.0", "Model": "COMPLETED", "Hardware Type": "M2", "CPU Type": "8.0", "CPU Cores": "8.0", "GPU Cores": "8.0", "Memory": "256.0", "Hard Drive": null, "Status": "INCLUDED", "Customer": "NEW", "Country": null, "PO": "A2337", "Receiving Date": null, "Condition": "ADP000", "Diagnostic": "MacBook Air 13\" Apple M2 8-Core CPU 8-Core GPU 8GB RAM 256GB SSD", "Erased": "Wise", "Keyboard": "SLYKN4DR4LV", "Charger": "IN STOCK", "Included": null}, {"Asset Tag": "25-Jul-24", "Serial Number": null, "Product": "MacBook Pro COMPLETED Apple 8.0", "Model": "COMPLETED", "Hardware Type": "M2", "CPU Type": "8.0", "CPU Cores": "8.0", "GPU Cores": "8.0", "Memory": "256.0", "Hard Drive": null, "Status": "INCLUDED", "Customer": "NEW", "Country": null, "PO": "A2337", "Receiving Date": null, "Condition": "ADP000", "Diagnostic": "MacBook Air 13\" Apple M2 8-Core CPU 8-Core GPU 8GB RAM 256GB SSD", "Erased": "Wise", "Keyboard": "SK1FMQMT493", "Charger": "IN STOCK", "Included": null}, {"Asset Tag": "25-Jul-24", "Serial Number": null, "Product": "MacBook Pro COMPLETED Apple 8.0", "Model": "COMPLETED", "Hardware Type": "M2", "CPU Type": "8.0", "CPU Cores": "8.0", "GPU Cores": "8.0", "Memory": "256.0", "Hard Drive": null, "Status": "INCLUDED", "Customer": "NEW", "Country": null, "PO": "A2337", "Receiving Date": null, "Condition": "ADP000", "Diagnostic": "MacBook Air 13\" Apple M2 8-Core CPU 8-Core GPU 8GB RAM 256GB SSD", "Erased": "Wise", "Keyboard": "SDQ367VDWW9", "Charger": "IN STOCK", "Included": null}, {"Asset Tag": "25-Jul-24", "Serial Number": null, "Product": "MacBook Pro COMPLETED Apple 8.0", "Model": "COMPLETED", "Hardware Type": "M2", "CPU Type": "8.0", "CPU Cores": "8.0", "GPU Cores": "8.0", "Memory": "256.0", "Hard Drive": null, "Status": "INCLUDED", "Customer": "NEW", "Country": null, "PO": "A2337", "Receiving Date": null, "Condition": "ADP000", "Diagnostic": "MacBook Air 13\" Apple M2 8-Core CPU 8-Core GPU 8GB RAM 256GB SSD", "Erased": "Wise", "Keyboard": "SMQ07VND6WW", "Charger": "IN STOCK", "Included": null}, {"Asset Tag": "25-Jul-24", "Serial Number": null, "Product": "MacBook Pro COMPLETED Apple 8.0", "Model": "COMPLETED", "Hardware Type": "M2", "CPU Type": "8.0", "CPU Cores": "8.0", "GPU Cores": "8.0", "Memory": "256.0", "Hard Drive": null, "Status": "INCLUDED", "Customer": "NEW", "Country": null, "PO": "A2337", "Receiving Date": null, "Condition": "ADP000", "Diagnostic": "MacBook Air 13\" Apple M2 8-Core CPU 8-Core GPU 8GB RAM 256GB SSD", "Erased": "Wise", "Keyboard": "SCV2N9FHT47", "Charger": "IN STOCK", "Included": null}, {"Asset Tag": "25-Jul-24", "Serial Number": null, "Product": "MacBook Pro COMPLETED Apple 8.0", "Model": "COMPLETED", "Hardware Type": "M2", "CPU Type": "8.0", "CPU Cores": "8.0", "GPU Cores": "8.0", "Memory": "256.0", "Hard Drive": null, "Status": "INCLUDED", "Customer": "NEW", "Country": null, "PO": "A2337", "Receiving Date": null, "Condition": "ADP000", "Diagnostic": "MacBook Air 13\" Apple M2 8-Core CPU 8-Core GPU 8GB RAM 256GB SSD", "Erased": "Wise", "Keyboard": "SL70G4066LF", "Charger": "IN STOCK", "Included": null}, {"Asset Tag": "25-Jul-24", "Serial Number": null, "Product": "MacBook Pro COMPLETED Apple 8.0", "Model": "COMPLETED", "Hardware Type": "M2", "CPU Type": "8.0", "CPU Cores": "8.0", "GPU Cores": "8.0", "Memory": "256.0", "Hard Drive": null, "Status": "INCLUDED", "Customer": "NEW", "Country": null, "PO": "A2337", "Receiving Date": null, "Condition": "ADP000", "Diagnostic": "MacBook Air 13\" Apple M2 8-Core CPU 8-Core GPU 8GB RAM 256GB SSD", "Erased": "Wise", "Keyboard": "SFPM74T19Q1", "Charger": "IN STOCK", "Included": null}, {"Asset Tag": "25-Jul-24", "Serial Number": null, "Product": "MacBook Pro COMPLETED Apple 8.0", "Model": "COMPLETED", "Hardware Type": "M2", "CPU Type": "8.0", "CPU Cores": "8.0", "GPU Cores": "8.0", "Memory": "256.0", "Hard Drive": null, "Status": "INCLUDED", "Customer": "NEW", "Country": null, "PO": "A2337", "Receiving Date": null, "Condition": "ADP000", "Diagnostic": "MacBook Air 13\" Apple M2 8-Core CPU 8-Core GPU 8GB RAM 256GB SSD", "Erased": "Wise", "Keyboard": "SHF25T7QC0H", "Charger": "IN STOCK", "Included": null}, {"Asset Tag": "25-Jul-24", "Serial Number": null, "Product": "MacBook Pro COMPLETED Apple 8.0", "Model": "COMPLETED", "Hardware Type": "M2", "CPU Type": "8.0", "CPU Cores": "8.0", "GPU Cores": "8.0", "Memory": "256.0", "Hard Drive": null, "Status": "INCLUDED", "Customer": "NEW", "Country": null, "PO": "A2337", "Receiving Date": null, "Condition": "ADP000", "Diagnostic": "MacBook Air 13\" Apple M2 8-Core CPU 8-Core GPU 8GB RAM 256GB SSD", "Erased": "Wise", "Keyboard": "SG7LCF1WMLY", "Charger": "IN STOCK", "Included": null}, {"Asset Tag": "25-Jul-24", "Serial Number": null, "Product": "MacBook Pro COMPLETED Apple 8.0", "Model": "COMPLETED", "Hardware Type": "M2", "CPU Type": "8.0", "CPU Cores": "8.0", "GPU Cores": "8.0", "Memory": "256.0", "Hard Drive": null, "Status": "INCLUDED", "Customer": "NEW", "Country": null, "PO": "A2337", "Receiving Date": null, "Condition": "ADP000", "Diagnostic": "MacBook Air 13\" Apple M2 8-Core CPU 8-Core GPU 8GB RAM 256GB SSD", "Erased": "Wise", "Keyboard": "SJXGJNPYFPK", "Charger": "IN STOCK", "Included": null}, {"Asset Tag": "25-Jul-24", "Serial Number": null, "Product": "MacBook Pro COMPLETED Apple 8.0", "Model": "COMPLETED", "Hardware Type": "M2", "CPU Type": "8.0", "CPU Cores": "8.0", "GPU Cores": "8.0", "Memory": "256.0", "Hard Drive": null, "Status": "INCLUDED", "Customer": "NEW", "Country": null, "PO": "A2337", "Receiving Date": null, "Condition": "ADP000", "Diagnostic": "MacBook Air 13\" Apple M2 8-Core CPU 8-Core GPU 8GB RAM 256GB SSD", "Erased": "Wise", "Keyboard": "SG7QQYLQXDP", "Charger": "IN STOCK", "Included": null}, {"Asset Tag": "25-Jul-24", "Serial Number": null, "Product": "MacBook Pro COMPLETED Apple 8.0", "Model": "COMPLETED", "Hardware Type": "M2", "CPU Type": "8.0", "CPU Cores": "8.0", "GPU Cores": "8.0", "Memory": "256.0", "Hard Drive": null, "Status": "INCLUDED", "Customer": "NEW", "Country": null, "PO": "A2337", "Receiving Date": null, "Condition": "ADP000", "Diagnostic": "MacBook Air 13\" Apple M2 8-Core CPU 8-Core GPU 8GB RAM 256GB SSD", "Erased": "Wise", "Keyboard": "SKWRGG9YW5P", "Charger": "IN STOCK", "Included": null}, {"Asset Tag": "25-Jul-24", "Serial Number": null, "Product": "MacBook Pro COMPLETED Apple 8.0", "Model": "COMPLETED", "Hardware Type": "M2", "CPU Type": "8.0", "CPU Cores": "8.0", "GPU Cores": "8.0", "Memory": "256.0", "Hard Drive": null, "Status": "INCLUDED", "Customer": "NEW", "Country": null, "PO": "A2337", "Receiving Date": null, "Condition": "ADP000", "Diagnostic": "MacBook Air 13\" Apple M2 8-Core CPU 8-Core GPU 8GB RAM 256GB SSD", "Erased": "Wise", "Keyboard": "SK72L4YHQ2G", "Charger": "IN STOCK", "Included": null}, {"Asset Tag": "25-Jul-24", "Serial Number": null, "Product": "MacBook Pro COMPLETED Apple 8.0", "Model": "COMPLETED", "Hardware Type": "M2", "CPU Type": "8.0", "CPU Cores": "8.0", "GPU Cores": "8.0", "Memory": "256.0", "Hard Drive": null, "Status": "INCLUDED", "Customer": "NEW", "Country": null, "PO": "A2337", "Receiving Date": null, "Condition": "ADP000", "Diagnostic": "MacBook Air 13\" Apple M2 8-Core CPU 8-Core GPU 8GB RAM 256GB SSD", "Erased": "Wise", "Keyboard": "SL0Q44JYXL9", "Charger": "IN STOCK", "Included": null}, {"Asset Tag": "25-Jul-24", "Serial Number": null, "Product": "MacBook Pro COMPLETED Apple 8.0", "Model": "COMPLETED", "Hardware Type": "M2", "CPU Type": "8.0", "CPU Cores": "8.0", "GPU Cores": "8.0", "Memory": "256.0", "Hard Drive": null, "Status": "INCLUDED", "Customer": "NEW", "Country": null, "PO": "A2337", "Receiving Date": null, "Condition": "ADP000", "Diagnostic": "MacBook Air 13\" Apple M2 8-Core CPU 8-Core GPU 8GB RAM 256GB SSD", "Erased": "Wise", "Keyboard": "SJ2KH72Q3KD", "Charger": "IN STOCK", "Included": null}, {"Asset Tag": "25-Jul-24", "Serial Number": null, "Product": "MacBook Pro COMPLETED Apple 8.0", "Model": "COMPLETED", "Hardware Type": "M2", "CPU Type": "8.0", "CPU Cores": "8.0", "GPU Cores": "8.0", "Memory": "256.0", "Hard Drive": null, "Status": "INCLUDED", "Customer": "NEW", "Country": null, "PO": "A2337", "Receiving Date": null, "Condition": "ADP000", "Diagnostic": "MacBook Air 13\" Apple M2 8-Core CPU 8-Core GPU 8GB RAM 256GB SSD", "Erased": "Wise", "Keyboard": "SLQR4TH5KFQ", "Charger": "IN STOCK", "Included": null}, {"Asset Tag": "25-Jul-24", "Serial Number": null, "Product": "MacBook Pro COMPLETED Apple 8.0", "Model": "COMPLETED", "Hardware Type": "M2", "CPU Type": "8.0", "CPU Cores": "8.0", "GPU Cores": "8.0", "Memory": "256.0", "Hard Drive": null, "Status": "INCLUDED", "Customer": "NEW", "Country": null, "PO": "A2337", "Receiving Date": null, "Condition": "ADP000", "Diagnostic": "MacBook Air 13\" Apple M2 8-Core CPU 8-Core GPU 8GB RAM 256GB SSD", "Erased": "Wise", "Keyboard": "SH5Y63X9F7X", "Charger": "IN STOCK", "Included": null}, {"Asset Tag": "25-Jul-24", "Serial Number": null, "Product": "MacBook Pro COMPLETED Apple 8.0", "Model": "COMPLETED", "Hardware Type": "M2", "CPU Type": "8.0", "CPU Cores": "8.0", "GPU Cores": "8.0", "Memory": "256.0", "Hard Drive": null, "Status": "INCLUDED", "Customer": "NEW", "Country": null, "PO": "A2337", "Receiving Date": null, "Condition": "ADP000", "Diagnostic": "MacBook Air 13\" Apple M2 8-Core CPU 8-Core GPU 8GB RAM 256GB SSD", "Erased": "Wise", "Keyboard": "SGWC7F2TG6N", "Charger": "IN STOCK", "Included": null}, {"Asset Tag": "25-Jul-24", "Serial Number": null, "Product": "MacBook Pro COMPLETED Apple 8.0", "Model": "COMPLETED", "Hardware Type": "M2", "CPU Type": "8.0", "CPU Cores": "8.0", "GPU Cores": "8.0", "Memory": "256.0", "Hard Drive": null, "Status": "INCLUDED", "Customer": "NEW", "Country": null, "PO": "A2337", "Receiving Date": null, "Condition": "ADP000", "Diagnostic": "MacBook Air 13\" Apple M2 8-Core CPU 8-Core GPU 8GB RAM 256GB SSD", "Erased": "Wise", "Keyboard": "SH6V3KHWMC6", "Charger": "IN STOCK", "Included": null}, {"Asset Tag": "25-Jul-24", "Serial Number": null, "Product": "MacBook Pro COMPLETED Apple 8.0", "Model": "COMPLETED", "Hardware Type": "M2", "CPU Type": "8.0", "CPU Cores": "8.0", "GPU Cores": "8.0", "Memory": "256.0", "Hard Drive": null, "Status": "INCLUDED", "Customer": "NEW", "Country": null, "PO": "A2337", "Receiving Date": null, "Condition": "ADP000", "Diagnostic": "MacBook Air 13\" Apple M2 8-Core CPU 8-Core GPU 8GB RAM 256GB SSD", "Erased": "Wise", "Keyboard": "SDCJWVCVQJD", "Charger": "IN STOCK", "Included": null}, {"Asset Tag": "", "Serial Number": null, "Product": "MacBook Pro COMPLETED Apple 8.0", "Model": "COMPLETED", "Hardware Type": "M2", "CPU Type": "8.0", "CPU Cores": "8.0", "GPU Cores": "8.0", "Memory": "256.0", "Hard Drive": null, "Status": "INCLUDED", "Customer": "NEW", "Country": null, "PO": "A2337", "Receiving Date": null, "Condition": "ADP000", "Diagnostic": "MacBook Air 13\" Apple M2 8-Core CPU 8-Core GPU 8GB RAM 256GB SSD", "Erased": "Wise", "Keyboard": "SK3PP7CHY66", "Charger": "IN STOCK", "Included": null}, {"Asset Tag": "25-Jul-24", "Serial Number": null, "Product": "MacBook Pro COMPLETED Apple 8.0", "Model": "COMPLETED", "Hardware Type": "M2", "CPU Type": "8.0", "CPU Cores": "8.0", "GPU Cores": "8.0", "Memory": "256.0", "Hard Drive": null, "Status": "INCLUDED", "Customer": "NEW", "Country": null, "PO": "A2337", "Receiving Date": null, "Condition": "ADP000", "Diagnostic": "MacBook Air 13\" Apple M2 8-Core CPU 8-Core GPU 8GB RAM 256GB SSD", "Erased": "Wise", "Keyboard": "SJK7KK6JQKP", "Charger": "IN STOCK", "Included": null}, {"Asset Tag": "25-Jul-24", "Serial Number": null, "Product": "MacBook Pro COMPLETED Apple 8.0", "Model": "COMPLETED", "Hardware Type": "M2", "CPU Type": "8.0", "CPU Cores": "8.0", "GPU Cores": "8.0", "Memory": "256.0", "Hard Drive": null, "Status": "INCLUDED", "Customer": "NEW", "Country": null, "PO": "A2337", "Receiving Date": null, "Condition": "ADP000", "Diagnostic": "MacBook Air 13\" Apple M2 8-Core CPU 8-Core GPU 8GB RAM 256GB SSD", "Erased": "Wise", "Keyboard": "SKNWGT9LJDF", "Charger": "IN STOCK", "Included": null}, {"Asset Tag": "25-Jul-24", "Serial Number": null, "Product": "MacBook Pro COMPLETED Apple 8.0", "Model": "COMPLETED", "Hardware Type": "M2", "CPU Type": "8.0", "CPU Cores": "8.0", "GPU Cores": "8.0", "Memory": "256.0", "Hard Drive": null, "Status": "INCLUDED", "Customer": "NEW", "Country": null, "PO": "A2337", "Receiving Date": null, "Condition": "ADP000", "Diagnostic": "MacBook Air 13\" Apple M2 8-Core CPU 8-Core GPU 8GB RAM 256GB SSD", "Erased": "Wise", "Keyboard": "SL6XTHPKT4C", "Charger": "IN STOCK", "Included": null}, {"Asset Tag": "25-Jul-24", "Serial Number": null, "Product": "MacBook Pro COMPLETED Apple 8.0", "Model": "COMPLETED", "Hardware Type": "M2", "CPU Type": "8.0", "CPU Cores": "8.0", "GPU Cores": "8.0", "Memory": "256.0", "Hard Drive": null, "Status": "INCLUDED", "Customer": "NEW", "Country": null, "PO": "A2337", "Receiving Date": null, "Condition": "ADP000", "Diagnostic": "MacBook Air 13\" Apple M2 8-Core CPU 8-Core GPU 8GB RAM 256GB SSD", "Erased": "Wise", "Keyboard": "SDH27CN6G6H", "Charger": "IN STOCK", "Included": null}, {"Asset Tag": "25-Jul-24", "Serial Number": null, "Product": "MacBook Pro COMPLETED Apple 8.0", "Model": "COMPLETED", "Hardware Type": "M2", "CPU Type": "8.0", "CPU Cores": "8.0", "GPU Cores": "8.0", "Memory": "256.0", "Hard Drive": null, "Status": "INCLUDED", "Customer": "NEW", "Country": null, "PO": "A2337", "Receiving Date": null, "Condition": "ADP000", "Diagnostic": "MacBook Air 13\" Apple M2 8-Core CPU 8-Core GPU 8GB RAM 256GB SSD", "Erased": "Wise", "Keyboard": "SHQJHPV2XNN", "Charger": "IN STOCK", "Included": null}, {"Asset Tag": "25-Jul-24", "Serial Number": null, "Product": "MacBook Pro COMPLETED Apple 8.0", "Model": "COMPLETED", "Hardware Type": "M2", "CPU Type": "8.0", "CPU Cores": "8.0", "GPU Cores": "8.0", "Memory": "256.0", "Hard Drive": null, "Status": "INCLUDED", "Customer": "NEW", "Country": null, "PO": "A2337", "Receiving Date": null, "Condition": "ADP000", "Diagnostic": "MacBook Air 13\" Apple M2 8-Core CPU 8-Core GPU 8GB RAM 256GB SSD", "Erased": "Wise", "Keyboard": "SC9TCG2Q1JP", "Charger": "IN STOCK", "Included": null}, {"Asset Tag": "25-Jul-24", "Serial Number": null, "Product": "MacBook Pro COMPLETED Apple 8.0", "Model": "COMPLETED", "Hardware Type": "M2", "CPU Type": "8.0", "CPU Cores": "8.0", "GPU Cores": "8.0", "Memory": "256.0", "Hard Drive": null, "Status": "INCLUDED", "Customer": "NEW", "Country": null, "PO": "A2337", "Receiving Date": null, "Condition": "ADP000", "Diagnostic": "MacBook Air 13\" Apple M2 8-Core CPU 8-Core GPU 8GB RAM 256GB SSD", "Erased": "Wise", "Keyboard": "SKJTPWM4C9P", "Charger": "IN STOCK", "Included": null}, {"Asset Tag": "25-Jul-24", "Serial Number": null, "Product": "MacBook Pro COMPLETED Apple 8.0", "Model": "COMPLETED", "Hardware Type": "M2", "CPU Type": "8.0", "CPU Cores": "8.0", "GPU Cores": "8.0", "Memory": "256.0", "Hard Drive": null, "Status": "INCLUDED", "Customer": "NEW", "Country": null, "PO": "A2337", "Receiving Date": null, "Condition": "ADP000", "Diagnostic": "MacBook Air 13\" Apple M2 8-Core CPU 8-Core GPU 8GB RAM 256GB SSD", "Erased": "Wise", "Keyboard": "SK7TD9K1GKL", "Charger": "IN STOCK", "Included": null}, {"Asset Tag": "25-Jul-24", "Serial Number": null, "Product": "MacBook Pro COMPLETED Apple 8.0", "Model": "COMPLETED", "Hardware Type": "M2", "CPU Type": "8.0", "CPU Cores": "8.0", "GPU Cores": "8.0", "Memory": "256.0", "Hard Drive": null, "Status": "INCLUDED", "Customer": "NEW", "Country": null, "PO": "A2337", "Receiving Date": null, "Condition": "ADP000", "Diagnostic": "MacBook Air 13\" Apple M2 8-Core CPU 8-Core GPU 8GB RAM 256GB SSD", "Erased": "Wise", "Keyboard": "SGG9X5WGJHN", "Charger": "IN STOCK", "Included": null}, {"Asset Tag": "25-Jul-24", "Serial Number": null, "Product": "MacBook Pro COMPLETED Apple 8.0", "Model": "COMPLETED", "Hardware Type": "M2", "CPU Type": "8.0", "CPU Cores": "8.0", "GPU Cores": "8.0", "Memory": "256.0", "Hard Drive": null, "Status": "INCLUDED", "Customer": "NEW", "Country": null, "PO": "A2681", "Receiving Date": null, "Condition": "ADP000", "Diagnostic": "0 M2 8-Core CPU 8-Core GPU 8GB RAM 256GB SSD", "Erased": "Wise", "Keyboard": "SKW0C4G4HGY", "Charger": "IN STOCK", "Included": null}, {"Asset Tag": "25-Jul-24", "Serial Number": null, "Product": "MacBook Pro COMPLETED Apple 8.0", "Model": "COMPLETED", "Hardware Type": "M2", "CPU Type": "8.0", "CPU Cores": "8.0", "GPU Cores": "8.0", "Memory": "256.0", "Hard Drive": null, "Status": "INCLUDED", "Customer": "NEW", "Country": null, "PO": "A2681", "Receiving Date": null, "Condition": "ADP000", "Diagnostic": "MacBook Air 13\" Apple M2 8-Core CPU 8-Core GPU 8GB RAM 256GB SSD", "Erased": "Wise", "Keyboard": "SJ6DKFCNKF6", "Charger": "IN STOCK", "Included": null}, {"Asset Tag": "25-Jul-24", "Serial Number": null, "Product": "MacBook Pro COMPLETED Apple 8.0", "Model": "COMPLETED", "Hardware Type": "M2", "CPU Type": "8.0", "CPU Cores": "8.0", "GPU Cores": "8.0", "Memory": "256.0", "Hard Drive": null, "Status": "INCLUDED", "Customer": "NEW", "Country": null, "PO": "A2681", "Receiving Date": null, "Condition": "ADP000", "Diagnostic": "MacBook Air 13\" Apple M2 8-Core CPU 8-Core GPU 8GB RAM 256GB SSD", "Erased": "Wise", "Keyboard": "SJ6R1FW376H", "Charger": "IN STOCK", "Included": null}, {"Asset Tag": "25-Jul-24", "Serial Number": null, "Product": "MacBook Pro COMPLETED Apple 8.0", "Model": "COMPLETED", "Hardware Type": "M2", "CPU Type": "8.0", "CPU Cores": "8.0", "GPU Cores": "8.0", "Memory": "256.0", "Hard Drive": null, "Status": "INCLUDED", "Customer": "NEW", "Country": null, "PO": "A2337", "Receiving Date": null, "Condition": "ADP000", "Diagnostic": "MacBook Air 13\" Apple M2 8-Core CPU 8-Core GPU 8GB RAM 256GB SSD", "Erased": "Wise", "Keyboard": "SJ2M4R9T2HQ", "Charger": "IN STOCK", "Included": null}, {"Asset Tag": "25-Jul-24", "Serial Number": null, "Product": "MacBook Pro COMPLETED Apple 8.0", "Model": "COMPLETED", "Hardware Type": "M2", "CPU Type": "8.0", "CPU Cores": "8.0", "GPU Cores": "8.0", "Memory": "256.0", "Hard Drive": null, "Status": "INCLUDED", "Customer": "NEW", "Country": null, "PO": "A2681", "Receiving Date": null, "Condition": "ADP000", "Diagnostic": "MacBook Air 13\" Apple M2 8-Core CPU 8-Core GPU 8GB RAM 256GB SSD", "Erased": "Wise", "Keyboard": "SC3H77K2H7D", "Charger": "IN STOCK", "Included": null}, {"Asset Tag": "25-Jul-24", "Serial Number": null, "Product": "MacBook Pro COMPLETED Apple 8.0", "Model": "COMPLETED", "Hardware Type": "M2", "CPU Type": "8.0", "CPU Cores": "8.0", "GPU Cores": "8.0", "Memory": "256.0", "Hard Drive": null, "Status": "INCLUDED", "Customer": "NEW", "Country": null, "PO": "A2337", "Receiving Date": null, "Condition": "ADP000", "Diagnostic": "MacBook Air 13\" Apple M2 8-Core CPU 8-Core GPU 8GB RAM 256GB SSD", "Erased": "Wise", "Keyboard": "SM5PH4F2FHF", "Charger": "IN STOCK", "Included": null}, {"Asset Tag": "25-Jul-24", "Serial Number": null, "Product": "MacBook Pro COMPLETED Apple 8.0", "Model": "COMPLETED", "Hardware Type": "M2", "CPU Type": "8.0", "CPU Cores": "8.0", "GPU Cores": "8.0", "Memory": "256.0", "Hard Drive": null, "Status": "INCLUDED", "Customer": "NEW", "Country": null, "PO": "A2681", "Receiving Date": null, "Condition": "ADP000", "Diagnostic": "MacBook Air 13\" Apple M2 8-Core CPU 8-Core GPU 8GB RAM 256GB SSD", "Erased": "Wise", "Keyboard": "SH70T6FMGFV", "Charger": "IN STOCK", "Included": null}, {"Asset Tag": "11-Apr-24", "Serial Number": null, "Product": "MacBook Pro COMPLETED Apple 11.0", "Model": "COMPLETED", "Hardware Type": "M3 Pro", "CPU Type": "11.0", "CPU Cores": "14.0", "GPU Cores": "18.0", "Memory": "512.0", "Hard Drive": null, "Status": "INCLUDED", "Customer": "NEW", "Country": null, "PO": "A2992", "Receiving Date": null, "Condition": "ADP000", "Diagnostic": "MacBook Pro 14\" Apple M3 Pro 11-Core CPU 14-Core GPU 18GB RAM 512GB SSD", "Erased": "Uipath", "Keyboard": "SDDWPDHF62W", "Charger": "IN STOCK", "Included": null}, {"Asset Tag": null, "Serial Number": null, "Product": "MacBook Pro COMPLETED Apple 11.0", "Model": "COMPLETED", "Hardware Type": "M3 Pro", "CPU Type": "11.0", "CPU Cores": "14.0", "GPU Cores": "18.0", "Memory": "512.0", "Hard Drive": null, "Status": "INCLUDED", "Customer": "NEW", "Country": null, "PO": "A2992", "Receiving Date": null, "Condition": "ADP000", "Diagnostic": "MacBook Pro 14\" Apple M3 Pro 11-Core CPU 14-Core GPU 18GB RAM 512GB SSD", "Erased": "Abnormal Security", "Keyboard": "SM9NPH4VNLJ", "Charger": "IN STOCK", "Included": null}, {"Asset Tag": null, "Serial Number": null, "Product": "MacBook Pro COMPLETED Apple 11.0", "Model": "COMPLETED", "Hardware Type": "M3 Pro", "CPU Type": "11.0", "CPU Cores": "14.0", "GPU Cores": "18.0", "Memory": "512.0", "Hard Drive": null, "Status": "INCLUDED", "Customer": "NEW", "Country": null, "PO": "A2442", "Receiving Date": null, "Condition": "ADP000", "Diagnostic": "MacBook Pro 14\" Apple M3 Pro 11-Core CPU 14-Core GPU 18GB RAM 512GB SSD", "Erased": "Abnormal Security", "Keyboard": "SL4XR6DM09P", "Charger": "IN STOCK", "Included": null}, {"Asset Tag": null, "Serial Number": null, "Product": "MacBook Pro COMPLETED Apple None", "Model": "COMPLETED", "Hardware Type": null, "CPU Type": null, "CPU Cores": null, "GPU Cores": null, "Memory": null, "Hard Drive": null, "Status": "INCLUDED", "Customer": "NEW", "Country": null, "PO": "A2681", "Receiving Date": null, "Condition": "ADP000", "Diagnostic": null, "Erased": "Sprout Social", "Keyboard": "SLT6DCVH6GJ", "Charger": "IN STOCK", "Included": null}, {"Asset Tag": "25-Jul-24", "Serial Number": null, "Product": "MacBook Pro COMPLETED Apple 8.0", "Model": "COMPLETED", "Hardware Type": "M2", "CPU Type": "8.0", "CPU Cores": "8.0", "GPU Cores": "8.0", "Memory": "256.0", "Hard Drive": null, "Status": "INCLUDED", "Customer": "NEW", "Country": null, "PO": "A2337", "Receiving Date": null, "Condition": "ADP000", "Diagnostic": "MacBook Air 13\" Apple M2 8-Core CPU 8-Core GPU 8GB RAM 256GB SSD", "Erased": "Wise", "Keyboard": "SLXQLGCXVY9", "Charger": "IN STOCK", "Included": null}, {"Asset Tag": "25-Jul-24", "Serial Number": null, "Product": "MacBook Pro COMPLETED Apple 8.0", "Model": "COMPLETED", "Hardware Type": "M2", "CPU Type": "8.0", "CPU Cores": "8.0", "GPU Cores": "8.0", "Memory": "256.0", "Hard Drive": null, "Status": "INCLUDED", "Customer": "NEW", "Country": null, "PO": "A2337", "Receiving Date": null, "Condition": "ADP000", "Diagnostic": "MacBook Air 13\" Apple M2 8-Core CPU 8-Core GPU 8GB RAM 256GB SSD", "Erased": "Wise", "Keyboard": "SK7WMQQ67GK", "Charger": "IN STOCK", "Included": null}, {"Asset Tag": "25-Jul-24", "Serial Number": null, "Product": "MacBook Pro COMPLETED Apple 8.0", "Model": "COMPLETED", "Hardware Type": "M2", "CPU Type": "8.0", "CPU Cores": "8.0", "GPU Cores": "8.0", "Memory": "256.0", "Hard Drive": null, "Status": "INCLUDED", "Customer": "NEW", "Country": null, "PO": "A2337", "Receiving Date": null, "Condition": "ADP000", "Diagnostic": "MacBook Air 13\" Apple M2 8-Core CPU 8-Core GPU 8GB RAM 256GB SSD", "Erased": "Wise", "Keyboard": "SFNW1CP2XJ0", "Charger": "IN STOCK", "Included": null}, {"Asset Tag": "25-Jul-24", "Serial Number": null, "Product": "MacBook Pro COMPLETED Apple 8.0", "Model": "COMPLETED", "Hardware Type": "M2", "CPU Type": "8.0", "CPU Cores": "8.0", "GPU Cores": "8.0", "Memory": "256.0", "Hard Drive": null, "Status": "INCLUDED", "Customer": "NEW", "Country": null, "PO": "A2337", "Receiving Date": null, "Condition": "ADP000", "Diagnostic": "MacBook Air 13\" Apple M2 8-Core CPU 8-Core GPU 8GB RAM 256GB SSD", "Erased": "Wise", "Keyboard": "SGK60L2DFVJ", "Charger": "IN STOCK", "Included": null}, {"Asset Tag": "25-Jul-24", "Serial Number": null, "Product": "MacBook Pro COMPLETED Apple 8.0", "Model": "COMPLETED", "Hardware Type": "M2", "CPU Type": "8.0", "CPU Cores": "8.0", "GPU Cores": "8.0", "Memory": "256.0", "Hard Drive": null, "Status": "INCLUDED", "Customer": "NEW", "Country": null, "PO": "A2337", "Receiving Date": null, "Condition": "ADP000", "Diagnostic": "MacBook Air 13\" Apple M2 8-Core CPU 8-Core GPU 8GB RAM 256GB SSD", "Erased": "Wise", "Keyboard": "SMHGX7C6Q0V", "Charger": "IN STOCK", "Included": null}, {"Asset Tag": "25-Jul-24", "Serial Number": null, "Product": "MacBook Pro COMPLETED Apple 8.0", "Model": "COMPLETED", "Hardware Type": "M2", "CPU Type": "8.0", "CPU Cores": "8.0", "GPU Cores": "8.0", "Memory": "256.0", "Hard Drive": null, "Status": "INCLUDED", "Customer": "NEW", "Country": null, "PO": "A2337", "Receiving Date": null, "Condition": "ADP000", "Diagnostic": "MacBook Air 13\" Apple M2 8-Core CPU 8-Core GPU 8GB RAM 256GB SSD", "Erased": "Wise", "Keyboard": "SMGQ1GL4THR", "Charger": "IN STOCK", "Included": null}, {"Asset Tag": "25-Jul-24", "Serial Number": null, "Product": "MacBook Pro COMPLETED Apple 8.0", "Model": "COMPLETED", "Hardware Type": "M2", "CPU Type": "8.0", "CPU Cores": "8.0", "GPU Cores": "8.0", "Memory": "256.0", "Hard Drive": null, "Status": "INCLUDED", "Customer": "NEW", "Country": null, "PO": "A2337", "Receiving Date": null, "Condition": "ADP000", "Diagnostic": "MacBook Air 13\" Apple M2 8-Core CPU 8-Core GPU 8GB RAM 256GB SSD", "Erased": "Wise", "Keyboard": "SH451652XW4", "Charger": "IN STOCK", "Included": null}, {"Asset Tag": "25-Jul-24", "Serial Number": null, "Product": "MacBook Pro COMPLETED Apple 8.0", "Model": "COMPLETED", "Hardware Type": "M2", "CPU Type": "8.0", "CPU Cores": "8.0", "GPU Cores": "8.0", "Memory": "256.0", "Hard Drive": null, "Status": "INCLUDED", "Customer": "NEW", "Country": null, "PO": "A2337", "Receiving Date": null, "Condition": "ADP000", "Diagnostic": "MacBook Air 13\" Apple M2 8-Core CPU 8-Core GPU 8GB RAM 256GB SSD", "Erased": "Wise", "Keyboard": "SL6GVV6X2VM", "Charger": "IN STOCK", "Included": null}, {"Asset Tag": "21-Feb-24", "Serial Number": null, "Product": "MacBook Pro COMPLETED Apple 8.0", "Model": "COMPLETED", "Hardware Type": "M2", "CPU Type": "8.0", "CPU Cores": "10.0", "GPU Cores": "16.0", "Memory": "256.0", "Hard Drive": null, "Status": "INCLUDED", "Customer": "NEW", "Country": null, "PO": "A2681", "Receiving Date": null, "Condition": "ADP000", "Diagnostic": "MacBook Air 13\" Apple M2 8-Core CPU 10-Core GPU 16GB RAM 256GB SSD", "Erased": "Sprout Social", "Keyboard": "SC2YHTGC4MM", "Charger": "IN STOCK", "Included": null}, {"Asset Tag": "21-Feb-24", "Serial Number": null, "Product": "MacBook Pro COMPLETED Apple 8.0", "Model": "COMPLETED", "Hardware Type": "M2", "CPU Type": "8.0", "CPU Cores": "8.0", "GPU Cores": "8.0", "Memory": "256.0", "Hard Drive": null, "Status": "INCLUDED", "Customer": "NEW", "Country": null, "PO": "A2681", "Receiving Date": null, "Condition": "ADP000", "Diagnostic": "MacBook Air 13\" Apple M2 8-Core CPU 8-Core GPU 8GB RAM 256GB SSD", "Erased": "Wise", "Keyboard": "SJ2DWQ3X0D4", "Charger": "IN STOCK", "Included": null}, {"Asset Tag": "21-Feb-24", "Serial Number": null, "Product": "MacBook Pro COMPLETED Apple 8.0", "Model": "COMPLETED", "Hardware Type": "M2", "CPU Type": "8.0", "CPU Cores": "8.0", "GPU Cores": "8.0", "Memory": "256.0", "Hard Drive": null, "Status": "INCLUDED", "Customer": "NEW", "Country": null, "PO": "A2681", "Receiving Date": null, "Condition": "ADP000", "Diagnostic": "MacBook Air 13\" Apple M2 8-Core CPU 8-Core GPU 8GB RAM 256GB SSD", "Erased": "Wise", "Keyboard": "SH2Y7X5146G", "Charger": "IN STOCK", "Included": null}, {"Asset Tag": "25-Jul-24", "Serial Number": null, "Product": "MacBook Pro COMPLETED Apple 12.0", "Model": "COMPLETED", "Hardware Type": "M3 Pro", "CPU Type": "12.0", "CPU Cores": "18.0", "GPU Cores": "36.0", "Memory": "512.0", "Hard Drive": null, "Status": "INCLUDED", "Customer": "NEW", "Country": null, "PO": "A2991", "Receiving Date": null, "Condition": "ADP000", "Diagnostic": "MacBook Pro 16\" Apple M3 Pro 12-Core CPU 18-Core GPU 36GB RAM 512GB SSD", "Erased": "Wise", "Keyboard": "SG75Y6KGQT4", "Charger": "IN STOCK", "Included": null}, {"Asset Tag": "25-Jul-24", "Serial Number": null, "Product": "MacBook Pro COMPLETED Apple 12.0", "Model": "COMPLETED", "Hardware Type": "M3 Pro", "CPU Type": "12.0", "CPU Cores": "18.0", "GPU Cores": "36.0", "Memory": "512.0", "Hard Drive": null, "Status": "INCLUDED", "Customer": "NEW", "Country": null, "PO": "A2991", "Receiving Date": null, "Condition": "ADP000", "Diagnostic": "MacBook Pro 16\" Apple M3 Pro 12-Core CPU 18-Core GPU 36GB RAM 512GB SSD", "Erased": "Wise", "Keyboard": "SGPT97WXQ01", "Charger": "IN STOCK", "Included": null}, {"Asset Tag": "25-Jul-24", "Serial Number": null, "Product": "MacBook Pro COMPLETED Apple 12.0", "Model": "COMPLETED", "Hardware Type": "M3 Pro", "CPU Type": "12.0", "CPU Cores": "18.0", "GPU Cores": "36.0", "Memory": "512.0", "Hard Drive": null, "Status": "INCLUDED", "Customer": "NEW", "Country": null, "PO": "A2991", "Receiving Date": null, "Condition": "ADP000", "Diagnostic": "MacBook Pro 16\" Apple M3 Pro 12-Core CPU 18-Core GPU 36GB RAM 512GB SSD", "Erased": "Wise", "Keyboard": "SDQ2Y400F03", "Charger": "IN STOCK", "Included": null}, {"Asset Tag": "25-Jul-24", "Serial Number": null, "Product": "MacBook Pro COMPLETED Apple 12.0", "Model": "COMPLETED", "Hardware Type": "M3 Pro", "CPU Type": "12.0", "CPU Cores": "18.0", "GPU Cores": "36.0", "Memory": "512.0", "Hard Drive": null, "Status": "INCLUDED", "Customer": "NEW", "Country": null, "PO": "A2991", "Receiving Date": null, "Condition": "ADP000", "Diagnostic": "MacBook Pro 16\" Apple M3 Pro 12-Core CPU 18-Core GPU 36GB RAM 512GB SSD", "Erased": "Wise", "Keyboard": "SMW2QK0GQ9M", "Charger": "IN STOCK", "Included": null}, {"Asset Tag": "25-Jul-24", "Serial Number": null, "Product": "MacBook Pro COMPLETED Apple 12.0", "Model": "COMPLETED", "Hardware Type": "M3 Pro", "CPU Type": "12.0", "CPU Cores": "18.0", "GPU Cores": "36.0", "Memory": "512.0", "Hard Drive": null, "Status": "INCLUDED", "Customer": "NEW", "Country": null, "PO": "A2991", "Receiving Date": null, "Condition": "ADP000", "Diagnostic": "MacBook Pro 16\" Apple M3 Pro 12-Core CPU 18-Core GPU 36GB RAM 512GB SSD", "Erased": "Wise", "Keyboard": "SD5VV0RXV73", "Charger": "IN STOCK", "Included": null}, {"Asset Tag": "25-Jul-24", "Serial Number": null, "Product": "MacBook Pro COMPLETED Apple 12.0", "Model": "COMPLETED", "Hardware Type": "M3 Pro", "CPU Type": "12.0", "CPU Cores": "18.0", "GPU Cores": "36.0", "Memory": "512.0", "Hard Drive": null, "Status": "INCLUDED", "Customer": "NEW", "Country": null, "PO": "A2991", "Receiving Date": null, "Condition": "ADP000", "Diagnostic": "MacBook Pro 16\" Apple M3 Pro 12-Core CPU 18-Core GPU 36GB RAM 512GB SSD", "Erased": "Wise", "Keyboard": "SM4Y6V9F22H", "Charger": "IN STOCK", "Included": null}, {"Asset Tag": "25-Jul-24", "Serial Number": null, "Product": "MacBook Pro COMPLETED Apple 12.0", "Model": "COMPLETED", "Hardware Type": "M3 Pro", "CPU Type": "12.0", "CPU Cores": "18.0", "GPU Cores": "36.0", "Memory": "512.0", "Hard Drive": null, "Status": "INCLUDED", "Customer": "NEW", "Country": null, "PO": "A2991", "Receiving Date": null, "Condition": "ADP000", "Diagnostic": "MacBook Pro 16\" Apple M3 Pro 12-Core CPU 18-Core GPU 36GB RAM 512GB SSD", "Erased": "Wise", "Keyboard": "SJ0K7HYY07G", "Charger": "IN STOCK", "Included": null}, {"Asset Tag": "25-Jul-24", "Serial Number": null, "Product": "MacBook Pro COMPLETED Apple 12.0", "Model": "COMPLETED", "Hardware Type": "M3 Pro", "CPU Type": "12.0", "CPU Cores": "18.0", "GPU Cores": "36.0", "Memory": "512.0", "Hard Drive": null, "Status": "INCLUDED", "Customer": "NEW", "Country": null, "PO": "A2991", "Receiving Date": null, "Condition": "ADP000", "Diagnostic": "MacBook Pro 16\" Apple M3 Pro 12-Core CPU 18-Core GPU 36GB RAM 512GB SSD", "Erased": "Wise", "Keyboard": "SKJ92JQXWL3", "Charger": "IN STOCK", "Included": null}, {"Asset Tag": "25-Jul-24", "Serial Number": null, "Product": "MacBook Pro COMPLETED Apple 12.0", "Model": "COMPLETED", "Hardware Type": "M3 Pro", "CPU Type": "12.0", "CPU Cores": "18.0", "GPU Cores": "36.0", "Memory": "512.0", "Hard Drive": null, "Status": "INCLUDED", "Customer": "NEW", "Country": null, "PO": "A2991", "Receiving Date": null, "Condition": "ADP000", "Diagnostic": "MacBook Pro 16\" Apple M3 Pro 12-Core CPU 18-Core GPU 36GB RAM 512GB SSD", "Erased": "Wise", "Keyboard": "SJWGX9PXQ5M", "Charger": "IN STOCK", "Included": null}, {"Asset Tag": "25-Jul-24", "Serial Number": null, "Product": "MacBook Pro COMPLETED Apple 12.0", "Model": "COMPLETED", "Hardware Type": "M3 Pro", "CPU Type": "12.0", "CPU Cores": "18.0", "GPU Cores": "36.0", "Memory": "512.0", "Hard Drive": null, "Status": "INCLUDED", "Customer": "NEW", "Country": null, "PO": "A2991", "Receiving Date": null, "Condition": "ADP000", "Diagnostic": "MacBook Pro 16\" Apple M3 Pro 12-Core CPU 18-Core GPU 36GB RAM 512GB SSD", "Erased": "Wise", "Keyboard": "SD9XXG45J6N", "Charger": "IN STOCK", "Included": null}, {"Asset Tag": "03-Jun-24", "Serial Number": null, "Product": "MacBook Pro COMPLETED Apple 6.0", "Model": "COMPLETED", "Hardware Type": "M3", "CPU Type": "6.0", "CPU Cores": "10.0", "GPU Cores": "16.0", "Memory": "512.0", "Hard Drive": null, "Status": "INCLUDED", "Customer": "NEW", "Country": null, "PO": "A3114", "Receiving Date": null, "Condition": "ADP000", "Diagnostic": "MacBook Air 15\" Apple M3 6-Core CPU 10-Core GPU 16GB RAM 512GB SSD", "Erased": "Sift", "Keyboard": "SMKC6PJGC77", "Charger": "IN STOCK", "Included": null}, {"Asset Tag": "27-Mar-24", "Serial Number": null, "Product": "MacBook Pro COMPLETED Apple 11.0", "Model": "COMPLETED", "Hardware Type": "M3 PRO", "CPU Type": "11.0", "CPU Cores": "14.0", "GPU Cores": "18.0", "Memory": "512.0", "Hard Drive": null, "Status": "INCLUDED", "Customer": "NEW", "Country": null, "PO": "A2992", "Receiving Date": null, "Condition": "ADP000", "Diagnostic": "MacBook Pro 14\" Apple M3 PRO 11-Core CPU 14-Core GPU 18GB RAM 512GB SSD", "Erased": "Abnormal Security", "Keyboard": "SK06K6W5YQT", "Charger": "IN STOCK", "Included": null}, {"Asset Tag": "27-Mar-24", "Serial Number": null, "Product": "MacBook Pro COMPLETED Apple 11.0", "Model": "COMPLETED", "Hardware Type": "M3 PRO", "CPU Type": "11.0", "CPU Cores": "14.0", "GPU Cores": "18.0", "Memory": "512.0", "Hard Drive": null, "Status": "INCLUDED", "Customer": "NEW", "Country": null, "PO": "A2992", "Receiving Date": null, "Condition": "ADP000", "Diagnostic": "MacBook Pro 14\" Apple M3 PRO 11-Core CPU 14-Core GPU 18GB RAM 512GB SSD", "Erased": "Abnormal Security", "Keyboard": "SJ14LYJRM2R", "Charger": "IN STOCK", "Included": null}, {"Asset Tag": "27-Mar-24", "Serial Number": null, "Product": "MacBook Pro COMPLETED Apple 11.0", "Model": "COMPLETED", "Hardware Type": "M3 PRO", "CPU Type": "11.0", "CPU Cores": "14.0", "GPU Cores": "18.0", "Memory": "512.0", "Hard Drive": null, "Status": "INCLUDED", "Customer": "NEW", "Country": null, "PO": "A2992", "Receiving Date": null, "Condition": "ADP000", "Diagnostic": "MacBook Pro 14\" Apple M3 PRO 11-Core CPU 14-Core GPU 18GB RAM 512GB SSD", "Erased": "Abnormal Security", "Keyboard": "SJHYPY6MDFR", "Charger": "IN STOCK", "Included": null}, {"Asset Tag": "27-Mar-24", "Serial Number": null, "Product": "MacBook Pro COMPLETED Apple 11.0", "Model": "COMPLETED", "Hardware Type": "M3 PRO", "CPU Type": "11.0", "CPU Cores": "14.0", "GPU Cores": "18.0", "Memory": "512.0", "Hard Drive": null, "Status": "INCLUDED", "Customer": "NEW", "Country": null, "PO": "A2992", "Receiving Date": null, "Condition": "ADP000", "Diagnostic": "MacBook Pro 14\" Apple M3 PRO 11-Core CPU 14-Core GPU 18GB RAM 512GB SSD", "Erased": "Abnormal Security", "Keyboard": "SMM670VW7V6", "Charger": "IN STOCK", "Included": null}, {"Asset Tag": "27-Mar-24", "Serial Number": null, "Product": "MacBook Pro COMPLETED Apple 11.0", "Model": "COMPLETED", "Hardware Type": "M3 PRO", "CPU Type": "11.0", "CPU Cores": "14.0", "GPU Cores": "18.0", "Memory": "512.0", "Hard Drive": null, "Status": "INCLUDED", "Customer": "NEW", "Country": null, "PO": "A2992", "Receiving Date": null, "Condition": "ADP000", "Diagnostic": "MacBook Pro 14\" Apple M3 PRO 11-Core CPU 14-Core GPU 18GB RAM 512GB SSD", "Erased": "Abnormal Security", "Keyboard": "SJVDPWDQGN2", "Charger": "IN STOCK", "Included": null}, {"Asset Tag": "27-Mar-24", "Serial Number": null, "Product": "MacBook Pro COMPLETED Apple 11.0", "Model": "COMPLETED", "Hardware Type": "M3 PRO", "CPU Type": "11.0", "CPU Cores": "14.0", "GPU Cores": "18.0", "Memory": "512.0", "Hard Drive": null, "Status": "INCLUDED", "Customer": "NEW", "Country": null, "PO": "A2992", "Receiving Date": null, "Condition": "ADP000", "Diagnostic": "MacBook Pro 14\" Apple M3 PRO 11-Core CPU 14-Core GPU 18GB RAM 512GB SSD", "Erased": "Abnormal Security", "Keyboard": "SMT26C637GP", "Charger": "IN STOCK", "Included": null}, {"Asset Tag": "27-Mar-24", "Serial Number": null, "Product": "MacBook Pro COMPLETED Apple 11.0", "Model": "COMPLETED", "Hardware Type": "M3 PRO", "CPU Type": "11.0", "CPU Cores": "14.0", "GPU Cores": "18.0", "Memory": "512.0", "Hard Drive": null, "Status": "INCLUDED", "Customer": "NEW", "Country": null, "PO": "A2992", "Receiving Date": null, "Condition": "ADP000", "Diagnostic": "MacBook Pro 14\" Apple M3 PRO 11-Core CPU 14-Core GPU 18GB RAM 512GB SSD", "Erased": "Abnormal Security", "Keyboard": "SKHGCJK4H7D", "Charger": "IN STOCK", "Included": null}, {"Asset Tag": "27-Mar-24", "Serial Number": null, "Product": "MacBook Pro COMPLETED Apple 11.0", "Model": "COMPLETED", "Hardware Type": "M3 PRO", "CPU Type": "11.0", "CPU Cores": "14.0", "GPU Cores": "18.0", "Memory": "512.0", "Hard Drive": null, "Status": "INCLUDED", "Customer": "NEW", "Country": null, "PO": "A2992", "Receiving Date": null, "Condition": "ADP000", "Diagnostic": "MacBook Pro 14\" Apple M3 PRO 11-Core CPU 14-Core GPU 18GB RAM 512GB SSD", "Erased": "Abnormal Security", "Keyboard": "SJ4Q6G34T97", "Charger": "IN STOCK", "Included": null}, {"Asset Tag": "27-Mar-24", "Serial Number": null, "Product": "MacBook Pro COMPLETED Apple 11.0", "Model": "COMPLETED", "Hardware Type": "M3 PRO", "CPU Type": "11.0", "CPU Cores": "14.0", "GPU Cores": "18.0", "Memory": "512.0", "Hard Drive": null, "Status": "INCLUDED", "Customer": "NEW", "Country": null, "PO": "A2992", "Receiving Date": null, "Condition": "ADP000", "Diagnostic": "MacBook Pro 14\" Apple M3 PRO 11-Core CPU 14-Core GPU 18GB RAM 512GB SSD", "Erased": "Abnormal Security", "Keyboard": "SHQG3RWQ31P", "Charger": "IN STOCK", "Included": null}, {"Asset Tag": "27-Mar-24", "Serial Number": null, "Product": "MacBook Pro COMPLETED Apple 11.0", "Model": "COMPLETED", "Hardware Type": "M3 PRO", "CPU Type": "11.0", "CPU Cores": "14.0", "GPU Cores": "18.0", "Memory": "512.0", "Hard Drive": null, "Status": "INCLUDED", "Customer": "NEW", "Country": null, "PO": "A2992", "Receiving Date": null, "Condition": "ADP000", "Diagnostic": "MacBook Pro 14\" Apple M3 PRO 11-Core CPU 14-Core GPU 18GB RAM 512GB SSD", "Erased": "Abnormal Security", "Keyboard": "SG2PW79P46L", "Charger": "IN STOCK", "Included": null}, {"Asset Tag": "27-Mar-24", "Serial Number": null, "Product": "MacBook Pro COMPLETED Apple 11.0", "Model": "COMPLETED", "Hardware Type": "M3 PRO", "CPU Type": "11.0", "CPU Cores": "14.0", "GPU Cores": "18.0", "Memory": "512.0", "Hard Drive": null, "Status": "INCLUDED", "Customer": "NEW", "Country": null, "PO": "A2992", "Receiving Date": null, "Condition": "ADP000", "Diagnostic": "MacBook Pro 14\" Apple M3 PRO 11-Core CPU 14-Core GPU 18GB RAM 512GB SSD", "Erased": "Abnormal Security", "Keyboard": "SHKF733JGVJ", "Charger": "IN STOCK", "Included": null}, {"Asset Tag": "27-Mar-24", "Serial Number": null, "Product": "MacBook Pro COMPLETED Apple 11.0", "Model": "COMPLETED", "Hardware Type": "M3 PRO", "CPU Type": "11.0", "CPU Cores": "14.0", "GPU Cores": "18.0", "Memory": "512.0", "Hard Drive": null, "Status": "INCLUDED", "Customer": "NEW", "Country": null, "PO": "A2992", "Receiving Date": null, "Condition": "ADP000", "Diagnostic": "MacBook Pro 14\" Apple M3 PRO 11-Core CPU 14-Core GPU 18GB RAM 512GB SSD", "Erased": "Abnormal Security", "Keyboard": "SL90NR2TCPY", "Charger": "IN STOCK", "Included": null}]